rlp/__init__.py
rlp/atomic.py
rlp/codec.py
rlp/exceptions.py
rlp/lazy.py
rlp/utils.py
rlp/sedes/__init__.py
rlp/sedes/big_endian_int.py
rlp/sedes/binary.py
rlp/sedes/boolean.py
rlp/sedes/lists.py
rlp/sedes/raw.py
rlp/sedes/serializable.py
rlp/sedes/text.py
rlp_cython/__init__.py
rlp_cython/atomic.py
rlp_cython/codec.py
rlp_cython/exceptions.py
rlp_cython/lazy.py
rlp_cython/utils.py
rlp_cython/sedes/__init__.py
rlp_cython/sedes/big_endian_int.py
rlp_cython/sedes/binary.py
rlp_cython/sedes/boolean.py
rlp_cython/sedes/lists.py
rlp_cython/sedes/raw.py
rlp_cython/sedes/serializable.py
rlp_cython/sedes/text.py
rlp_cython-2.1.7.dist-info/LICENSE
rlp_cython-2.1.7.dist-info/METADATA
rlp_cython-2.1.7.dist-info/WHEEL
rlp_cython-2.1.7.dist-info/top_level.txt
rlp_cython-2.1.7.dist-info/RECORD
