Metadata-Version: 2.1
Name: rlp-cython
Version: 2.1.7
Summary: A package for Recursive Length Prefix encoding and decoding
Home-page: https://github.com/Helios-Protocol/py-rlp-cython
Author: Tommy Mckinnon
Author-email: tommy@heliosprotocol.io
License: MIT
Keywords: rlp cython helios ethereum
Platform: UNKNOWN
Classifier: Intended Audience :: Developers
Classifier: License :: OSI Approved :: MIT License
Classifier: Natural Language :: English
Classifier: Programming Language :: Python :: 3
Classifier: Programming Language :: Python :: 3.5
Classifier: Programming Language :: Python :: 3.6
Classifier: Programming Language :: Python :: Implementation :: PyPy
Requires-Dist: msgpack-rlp (>=0.6.3)
Requires-Dist: eth-utils (<2,>=1.0.2)
Provides-Extra: dev
Requires-Dist: bumpversion (<1,>=0.5.3) ; extra == 'dev'
Requires-Dist: pytest-xdist ; extra == 'dev'
Requires-Dist: pytest-watch (<5,>=4.1.0) ; extra == 'dev'
Requires-Dist: wheel ; extra == 'dev'
Requires-Dist: ipython ; extra == 'dev'
Requires-Dist: twine ; extra == 'dev'
Requires-Dist: pytest (==3.3.2) ; extra == 'dev'
Requires-Dist: tox (<3,>=2.9.1) ; extra == 'dev'
Requires-Dist: hypothesis (==3.56.5) ; extra == 'dev'
Requires-Dist: flake8 (==3.4.1) ; extra == 'dev'
Requires-Dist: Sphinx (<2,>=1.6.5) ; extra == 'dev'
Requires-Dist: sphinx-rtd-theme (>=0.1.9) ; extra == 'dev'
Requires-Dist: msgpack-rlp (>=0.6.3) ; extra == 'dev'
Requires-Dist: eth-utils (<2,>=1.0.2) ; extra == 'dev'
Provides-Extra: doc
Requires-Dist: Sphinx (<2,>=1.6.5) ; extra == 'doc'
Requires-Dist: sphinx-rtd-theme (>=0.1.9) ; extra == 'doc'
Provides-Extra: lint
Requires-Dist: flake8 (==3.4.1) ; extra == 'lint'
Provides-Extra: test
Requires-Dist: pytest (==3.3.2) ; extra == 'test'
Requires-Dist: tox (<3,>=2.9.1) ; extra == 'test'
Requires-Dist: hypothesis (==3.56.5) ; extra == 'test'
